DATA/__init__.py
DATA/fips_lookup.csv
synmax/__init__.py
synmax/common/__init__.py
synmax/common/api_client.py
synmax/common/model.py
synmax/config/__init__.py
synmax/helpers/__init__.py
synmax/helpers/implicit_filters.py
synmax/hyperion/__init__.py
synmax/hyperion/create_simulation.py
synmax/hyperion/hyperion_client.py
synmax/hyperion/hyperion_payload.py
synmax/hyperion/process_api.py
synmax/hyperion/process_inputs.py
synmax/hyperion/v4/__init__.py
synmax/hyperion/v4/hyperion_client.py
synmax/hyperion/v4/hyperion_client.pyi
synmax/hyperion/v4/openapi.yaml
synmax/hyperion/v4/start_hyperion_client.py
synmax/leviaton/__init__.py
synmax/leviaton/start_leviaton_client.py
synmax/leviaton/start_leviaton_client2.py
synmax/leviaton/v1/__init__.py
synmax/leviaton/v1/leviaton_client.py
synmax/leviaton/v1/leviaton_client.pyi
synmax/leviaton/v1/openapi.yaml
synmax/openapi/__init__.py
synmax/openapi/client.py
synmax/openapi/utils.py
synmax/theia/__init__.py
synmax/vulcan/__init__.py
synmax/vulcan/start_vulcan_python_client.py
synmax/vulcan/v2/__init__.py
synmax/vulcan/v2/openapi.yaml
synmax/vulcan/v2/start_vulcan_client.py
synmax/vulcan/v2/start_vulcan_client2.py
synmax/vulcan/v2/vulcan_client.py
synmax/vulcan/v2/vulcan_client.pyi
test/__init__.py
test/test_api_client.py
test/test_hyperion_client.py
test/test_hyperion_e2e.py
test/test_hyperion_helpers.py
synmax_api_python_client-4.13.0.dist-info/LICENSE
synmax_api_python_client-4.13.0.dist-info/METADATA
synmax_api_python_client-4.13.0.dist-info/WHEEL
synmax_api_python_client-4.13.0.dist-info/top_level.txt
synmax_api_python_client-4.13.0.dist-info/RECORD
