Metadata-Version: 2.1
Name: synmax-api-python-client
Version: 4.13.0
Summary: Synmax API client
Home-page: https://github.com/SynMaxDev/synmax-api-python-client.git
Author: SynMax Inc.
Author-email: support@synmax.com
Requires-Python: >=3.7
License-File: LICENSE
Requires-Dist: aiohttp>=3.11.14
Requires-Dist: aioretry>=6.3.1
Requires-Dist: packaging>=24.2
Requires-Dist: pandas>=2.0.3
Requires-Dist: pydantic>=2.10.6
Requires-Dist: pydantic-core<2.32.0,>=2.27.2
Requires-Dist: requests>=2.32.3
Requires-Dist: tenacity>=9.0.0
Requires-Dist: tqdm>=4.67.1
Requires-Dist: urllib3>=2.3.0
Requires-Dist: prance>=25.4.8.0
Requires-Dist: openapi-spec-validator>=0.7.1
Requires-Dist: httpx>=0.28.1
